relativedate/__init__.py
relativedate/dtget.py
relativedate/dtmath.py
relativedate-1.3.3.dist-info/METADATA
relativedate-1.3.3.dist-info/WHEEL
relativedate-1.3.3.dist-info/top_level.txt
relativedate-1.3.3.dist-info/RECORD
