Metadata-Version: 2.1
Name: relativedate
Version: 1.3.3
Summary: Pacote Python para tabalhar com Datas Relativas
